advanced_sheet_label/__init__.py
advanced_sheet_label/layouts.py
advanced_sheet_label/printing_plugin.py
inventree_adv_sheet_label-1.3.1.dist-info/licenses/LICENSE
inventree_adv_sheet_label-1.3.1.dist-info/METADATA
inventree_adv_sheet_label-1.3.1.dist-info/WHEEL
inventree_adv_sheet_label-1.3.1.dist-info/entry_points.txt
inventree_adv_sheet_label-1.3.1.dist-info/top_level.txt
inventree_adv_sheet_label-1.3.1.dist-info/RECORD
