Metadata-Version: 2.4
Name: inventree-adv-sheet-label
Version: 1.3.1
Summary: A label printing plugin for InvenTree which provides support for printing labels on off-the-shelf label sheet layouts and adds some more useful features.
Author-email: melektron <matteo@elektron.work>
Project-URL: Homepage, https://github.com/melektron/inventree-adv-sheet-label
Project-URL: Issues, https://github.com/melektron/inventree-adv-sheet-label/issues
Classifier: Programming Language :: Python :: 3
Classifier: License :: OSI Approved :: MIT License
Classifier: Operating System :: OS Independent
Requires-Python: >=3.9
License-File: LICENSE
Dynamic: license-file
